biggo_api/__init__.py
biggo_api/exception.py
biggo_api/responses.py
biggo_api/async_clients/__init__.py
biggo_api/async_clients/_auth.py
biggo_api/async_clients/_base.py
biggo_api/async_clients/_user.py
biggo_api/async_clients/_video.py
biggo_api/async_clients/api.py
biggo_api/clients/__init__.py
biggo_api/clients/_auth.py
biggo_api/clients/_base.py
biggo_api/clients/_user.py
biggo_api/clients/_video.py
biggo_api/clients/api.py
biggo_api/data_models/__init__.py
biggo_api/data_models/product.py
biggo_api/data_models/user.py
biggo_api/data_models/video.py
biggo_api/enum/__init__.py
biggo_api/enum/access.py
biggo_api/enum/process_status.py
biggo_api-0.2.0.dist-info/LICENSE
biggo_api-0.2.0.dist-info/METADATA
biggo_api-0.2.0.dist-info/WHEEL
biggo_api-0.2.0.dist-info/top_level.txt
biggo_api-0.2.0.dist-info/RECORD
