Metadata-Version: 2.1
Name: biggo-api
Version: 0.2.0
Summary: client for accessing biggo api
Home-page: https://github.com/Funmula-Corp/biggo-api-python-client
Author: FUNMULA CO., LIMITED
Author-email: info@funmula.com
License: UNKNOWN
Keywords: BigGo,Funmula,API,Open-Authentication,Social-Media,Social-Networking
Platform: Linux
Platform: Windows
Platform: Mac
Classifier: Development Status :: 4 - Beta
Classifier: Environment :: Console
Classifier: Environment :: Web Environment
Classifier: Intended Audience :: Developers
Classifier: License :: OSI Approved :: MIT License
Classifier: Natural Language :: English
Classifier: Operating System :: MacOS :: MacOS X
Classifier: Operating System :: Microsoft :: Windows
Classifier: Operating System :: POSIX
Classifier: Programming Language :: Python
Classifier: Programming Language :: Python :: 3
Classifier: Programming Language :: Python :: 3.9
Classifier: Programming Language :: Python :: 3.10
Classifier: Programming Language :: Python :: 3.11
Classifier: Topic :: Communications
Classifier: Topic :: Software Development :: Libraries :: Python Modules
Requires-Python: >=3.9
License-File: LICENSE
